setup.cfg
setup.py
funcpy/__init__.py
funcpy/func.py
funcpy.egg-info/PKG-INFO
funcpy.egg-info/SOURCES.txt
funcpy.egg-info/dependency_links.txt
funcpy.egg-info/top_level.txt