Metadata-Version: 1.1
Name: funcpy
Version: 0.1.0
Summary: provide several functions to manipulate function
Home-page: https://github.com/xampre/funcpy
Author: Shogo Takayama
Author-email: xampre@vivaldi.net
License: MIT license
Platform: UNKNOWN
Classifier: Development Status :: 2 - Pre-Alpha
Classifier: License :: OSI Approved :: MIT License
Classifier: Programming Language :: Python :: 3.5
Classifier: Programming Language :: Python :: 3.6
